patchwork/Bundle.py
patchwork/Check.py
patchwork/Comment.py
patchwork/Connection.py
patchwork/Cover.py
patchwork/Pagination.py
patchwork/Patch.py
patchwork/Patchwork.py
patchwork/PatchworkException.py
patchwork/People.py
patchwork/Project.py
patchwork/Series.py
patchwork/User.py
patchwork/UserSettings.py
patchwork/__init__.py
tests/__init__.py
tests/test_Bundle.py
tests/test_Check.py
tests/test_Comment.py
tests/test_Connection.py
tests/test_Cover.py
tests/test_Pagination.py
tests/test_Patch.py
tests/test_Patchwork.py
tests/test_People.py
tests/test_Project.py
tests/test_Series.py
tests/test_User.py
PyPatchwork-0.1.0.dist-info/LICENSE
PyPatchwork-0.1.0.dist-info/METADATA
PyPatchwork-0.1.0.dist-info/WHEEL
PyPatchwork-0.1.0.dist-info/top_level.txt
PyPatchwork-0.1.0.dist-info/RECORD
